{
"type": "FeatureCollection",
"name": "Copper",
"crs": { "type": "name", "properties": { "name": "urn:ogc:def:crs:OGC:1.3:CRS84" } },
"features": [
{ "type": "Feature", "properties": { "lat": -25.526315789473685, "lon": 117.36842105263158, "mineral": "Copper", "probability": 0.15941142678743714, "mineral_1": "Copper", "prob_1": 0.15941142678743714, "mineral_2": "Germanium", "prob_2": 0.12931697040921994, "mineral_3": "Tantalum", "prob_3": 0.081576523223903144 }, "geometry": { "type": "Point", "coordinates": [ 117.368421052631575, -25.526315789473685 ] } },
{ "type": "Feature", "properties": { "lat": -25.526315789473685, "lon": 119.73684210526315, "mineral": "Copper", "probability": 0.13100024551494791, "mineral_1": "Copper", "prob_1": 0.13100024551494791, "mineral_2": "Germanium", "prob_2": 0.11919018139760656, "mineral_3": "Gallium", "prob_3": 0.086123253846951436 }, "geometry": { "type": "Point", "coordinates": [ 119.73684210526315, -25.526315789473685 ] } },
{ "type": "Feature", "properties": { "lat": -25.263157894736842, "lon": 115.0, "mineral": "Copper", "probability": 0.16282677844742935, "mineral_1": "Copper", "prob_1": 0.16282677844742935, "mineral_2": "Germanium", "prob_2": 0.15333402069990784, "mineral_3": "Cobalt", "prob_3": 0.088020528281621144 }, "geometry": { "type": "Point", "coordinates": [ 115.0, -25.263157894736842 ] } },
{ "type": "Feature", "properties": { "lat": -25.0, "lon": 115.26315789473684, "mineral": "Copper", "probability": 0.1528969665219142, "mineral_1": "Copper", "prob_1": 0.1528969665219142, "mineral_2": "Germanium", "prob_2": 0.12571773693555033, "mineral_3": "Tin", "prob_3": 0.10704481713907174 }, "geometry": { "type": "Point", "coordinates": [ 115.263157894736835, -25.0 ] } },
{ "type": "Feature", "properties": { "lat": -25.0, "lon": 115.78947368421052, "mineral": "Copper", "probability": 0.16305233788307194, "mineral_1": "Copper", "prob_1": 0.16305233788307194, "mineral_2": "Nickel", "prob_2": 0.13777964136695109, "mineral_3": "Cobalt", "prob_3": 0.10070743569672937 }, "geometry": { "type": "Point", "coordinates": [ 115.78947368421052, -25.0 ] } },
{ "type": "Feature", "properties": { "lat": -25.0, "lon": 118.15789473684211, "mineral": "Copper", "probability": 0.1590594412796435, "mineral_1": "Copper", "prob_1": 0.1590594412796435, "mineral_2": "Zirconium", "prob_2": 0.10551533247015378, "mineral_3": "Cobalt", "prob_3": 0.10235226946685923 }, "geometry": { "type": "Point", "coordinates": [ 118.15789473684211, -25.0 ] } },
{ "type": "Feature", "properties": { "lat": -25.0, "lon": 118.68421052631579, "mineral": "Copper", "probability": 0.13157048728562232, "mineral_1": "Copper", "prob_1": 0.13157048728562232, "mineral_2": "Cobalt", "prob_2": 0.12754837129155119, "mineral_3": "Tantalum", "prob_3": 0.12128855743261951 }, "geometry": { "type": "Point", "coordinates": [ 118.684210526315795, -25.0 ] } },
{ "type": "Feature", "properties": { "lat": -25.0, "lon": 118.94736842105263, "mineral": "Copper", "probability": 0.16082512541047772, "mineral_1": "Copper", "prob_1": 0.16082512541047772, "mineral_2": "Zirconium", "prob_2": 0.11980187630117028, "mineral_3": "Tantalum", "prob_3": 0.11516098381504565 }, "geometry": { "type": "Point", "coordinates": [ 118.94736842105263, -25.0 ] } },
{ "type": "Feature", "properties": { "lat": -25.0, "lon": 119.21052631578948, "mineral": "Copper", "probability": 0.17608133114047855, "mineral_1": "Copper", "prob_1": 0.17608133114047855, "mineral_2": "Zirconium", "prob_2": 0.15029365171701098, "mineral_3": "Germanium", "prob_3": 0.1373140621365275 }, "geometry": { "type": "Point", "coordinates": [ 119.21052631578948, -25.0 ] } },
{ "type": "Feature", "properties": { "lat": -25.0, "lon": 119.73684210526315, "mineral": "Copper", "probability": 0.15858330195183054, "mineral_1": "Copper", "prob_1": 0.15858330195183054, "mineral_2": "Zirconium", "prob_2": 0.15129914286817991, "mineral_3": "Cobalt", "prob_3": 0.10863559962563679 }, "geometry": { "type": "Point", "coordinates": [ 119.73684210526315, -25.0 ] } }
]
}
